bashrc-0.31.90.data/scripts/apt-kali.sh
bashrc-0.31.90.data/scripts/bash-wakatime.sh
bashrc-0.31.90.data/scripts/bashrc
bashrc-0.31.90.data/scripts/bashrc-aliases
bashrc-0.31.90.data/scripts/bashrc-completions
bashrc-0.31.90.data/scripts/bashrc-dirs
bashrc-0.31.90.data/scripts/bashrc-distro
bashrc-0.31.90.data/scripts/bashrc-functions
bashrc-0.31.90.data/scripts/bashrc-install.sh
bashrc-0.31.90.data/scripts/bashrc-iterm2
bashrc-0.31.90.data/scripts/bashrc-misc
bashrc-0.31.90.data/scripts/bashrc-paths
bashrc-0.31.90.data/scripts/bashrc-vars
bashrc-0.31.90.data/scripts/black.sh
bashrc-0.31.90.data/scripts/blue.sh
bashrc-0.31.90.data/scripts/clean.sh
bashrc-0.31.90.data/scripts/cyan.sh
bashrc-0.31.90.data/scripts/debug.sh
bashrc-0.31.90.data/scripts/docker.sh
bashrc-0.31.90.data/scripts/dpkg-local.sh
bashrc-0.31.90.data/scripts/error.sh
bashrc-0.31.90.data/scripts/essentials.sh
bashrc-0.31.90.data/scripts/filelimits.sh
bashrc-0.31.90.data/scripts/gadd.sh
bashrc-0.31.90.data/scripts/gall.sh
bashrc-0.31.90.data/scripts/gclone.sh
bashrc-0.31.90.data/scripts/gclonesrm.sh
bashrc-0.31.90.data/scripts/gcommit.sh
bashrc-0.31.90.data/scripts/gconfig.sh
bashrc-0.31.90.data/scripts/gmerge.sh
bashrc-0.31.90.data/scripts/gpull.sh
bashrc-0.31.90.data/scripts/gpush.sh
bashrc-0.31.90.data/scripts/green.sh
bashrc-0.31.90.data/scripts/grey.sh
bashrc-0.31.90.data/scripts/gtag.sh
bashrc-0.31.90.data/scripts/gtop
bashrc-0.31.90.data/scripts/home.sh
bashrc-0.31.90.data/scripts/homefiles.sh
bashrc-0.31.90.data/scripts/info.sh
bashrc-0.31.90.data/scripts/inputrc
bashrc-0.31.90.data/scripts/install-brew.sh
bashrc-0.31.90.data/scripts/isuser.sh
bashrc-0.31.90.data/scripts/isuserdarwin.sh
bashrc-0.31.90.data/scripts/logrotate.sh
bashrc-0.31.90.data/scripts/loop.sh
bashrc-0.31.90.data/scripts/magenta.sh
bashrc-0.31.90.data/scripts/manpaths.sh
bashrc-0.31.90.data/scripts/mongo.sh
bashrc-0.31.90.data/scripts/mongossh.sh
bashrc-0.31.90.data/scripts/motd.sh
bashrc-0.31.90.data/scripts/orange.sh
bashrc-0.31.90.dist-info/METADATA
bashrc-0.31.90.dist-info/WHEEL
bashrc-0.31.90.dist-info/top_level.txt
bashrc-0.31.90.dist-info/RECORD
