Metadata-Version: 2.1
Name: bashrc
Version: 0.31.90
Summary: UNKNOWN
Home-page: UNKNOWN
Author: UNKNOWN
Author-email: UNKNOWN
License: UNKNOWN
Platform: UNKNOWN
Requires-Dist: bump2version
Requires-Dist: config-path
Requires-Dist: devtools
Requires-Dist: furl
Requires-Dist: gitpython
Requires-Dist: icecream
Requires-Dist: intervaltree
Requires-Dist: pip
Requires-Dist: psutil
Requires-Dist: pydantic
Requires-Dist: python-box[all]
Requires-Dist: semver
Requires-Dist: setuptools
Requires-Dist: shell-proc
Requires-Dist: twine
Requires-Dist: typer
Requires-Dist: wheel
